mxio/__init__.py
mxio/formats/__init__.py
mxio/formats/cbf.py
mxio/formats/eiger.py
mxio/formats/hdf5.py
mxio/formats/mar345.py
mxio/formats/marccd.py
mxio/formats/nexus.py
mxio/formats/raxis.py
mxio/formats/smv.py
mxio/log.py
mxio/misc/__init__.py
mxio/misc/bshuf.py
mxio-2025.10.6.dist-info/METADATA
mxio-2025.10.6.dist-info/WHEEL
mxio-2025.10.6.dist-info/entry_points.txt
mxio-2025.10.6.dist-info/licenses/LICENSE
mxio-2025.10.6.dist-info/RECORD
