Metadata-Version: 2.4
Name: mxio
Version: 2025.10.6
Summary: A Simple X-ray Area Detector Data IO Library
License-Expression: MIT
License-File: LICENSE
Author: Michel Fodje
Author-email: michel4j@gmail.com
Requires-Python: >=3.9,<4.0
Classifier: License :: OSI Approved :: MIT License
Classifier: Programming Language :: Python :: 3
Requires-Dist: h5py
Requires-Dist: hdf5plugin
Requires-Dist: iso8601
Requires-Dist: lz4
Requires-Dist: numpy
Requires-Dist: opencv-python
Requires-Dist: parsefire
Requires-Dist: poetry-dynamic-versioning (>=1.0.0)
Requires-Dist: pycbf (>=0.9.6.7,<0.10.0.0)
Requires-Dist: python-magic
Requires-Dist: pytz
Requires-Dist: pyyaml
Requires-Dist: pyzmq
Requires-Dist: setuptools-scm
Project-URL: Homepage, https://github.com/michel4j/mxio
Project-URL: Issues, https://github.com/michel4j/mxio/issues
